gbase8sdb/__init__.py
gbase8sdb/column_metadata.py
gbase8sdb/connection.py
gbase8sdb/constructors.py
gbase8sdb/cursor.py
gbase8sdb/defaults.py
gbase8sdb/driver.cpython-311-aarch64-linux-gnu.so
gbase8sdb/dsn.py
gbase8sdb/errors.py
gbase8sdb/exceptions.py
gbase8sdb/lob.py
gbase8sdb/var.py
gbase8sdb/version.py
gbase8sdb-0.2.4.dist-info/LICENSE.txt
gbase8sdb-0.2.4.dist-info/METADATA
gbase8sdb-0.2.4.dist-info/THIRD_PARTY_LICENSES.txt
gbase8sdb-0.2.4.dist-info/WHEEL
gbase8sdb-0.2.4.dist-info/top_level.txt
gbase8sdb-0.2.4.dist-info/RECORD
