Metadata-Version: 2.1
Name: gbase8sdb
Version: 0.2.4
Summary: Python interface to GBase 8s Database
License: MIT
Keywords: GBase 8s,database
Classifier: Development Status :: 5 - Production/Stable
Classifier: Intended Audience :: Developers
Classifier: License :: OSI Approved :: MIT License
Classifier: Natural Language :: English
Classifier: Operating System :: OS Independent
Classifier: Programming Language :: Python :: 3 :: Only
Classifier: Programming Language :: Python :: Implementation :: CPython
Classifier: Programming Language :: Cython
Classifier: Topic :: Database
License-File: LICENSE.txt
License-File: THIRD_PARTY_LICENSES.txt
